{"type":"FeatureCollection","metadata":{"name":"Учреждения спорта","creator":"Yandex Map Constructor"},"features":[{"type":"Feature","id":0,"geometry":{"type":"Point","coordinates":[34.447937,53.865245]},"properties":{"description":"Школа олимпийского резерва «ТРИУМФ», г.Людиново, ул. площадь Победы д.2","iconCaption":"МКУ ДО СШОР «ТРИУМФ» им. М.А. Ухиной","marker-color":"#793d0e"}},{"type":"Feature","id":1,"geometry":{"type":"Point","coordinates":[34.446867,53.871085]},"properties":{"description":"г. Людиново, ул. К. Либкнехта 16 А","iconCaption":"Стадион Авангард","marker-color":"#793d0e"}},{"type":"Feature","id":2,"geometry":{"type":"Point","coordinates":[34.44802,53.865143]},"properties":{"description":"Универсальная спортплощадка, г. Людиново, ул. площадь Победы д.2А","iconCaption":"Универсальная спортплощадка","marker-color":"#793d0e"}},{"type":"Feature","id":3,"geometry":{"type":"Point","coordinates":[34.427001,53.848753]},"properties":{"description":"Спорткомплекс «Людиновский» Бассейн, г. Людиново, ул. Маяковского 103 Б","iconCaption":"Спорткомплекс «Людиновский» Бассейн","marker-color":"#793d0e"}},{"type":"Feature","id":4,"geometry":{"type":"Point","coordinates":[34.409626,53.838767]},"properties":{"description":"Школа олимпийского резерва «ТРИУМФ», г. Людиново, ул. Герцена 15 А","iconCaption":"МКУ ДО СШОР «ТРИУМФ» им. М.А. Ухиной","marker-color":"#793d0e"}},{"type":"Feature","id":5,"geometry":{"type":"Point","coordinates":[34.409626,53.838767]},"properties":{"description":"Универсальная спортплощадка, г. Людиново, ул. Герцена 15А","iconCaption":"Универсальная спортивная площадка","marker-color":"#793d0e"}},{"type":"Feature","id":6,"geometry":{"type":"Point","coordinates":[34.407079,53.837186]},"properties":{"description":"Спорткомплекс «ТРИУМФ», г. Людиново, улица Трудовые Резервы, 1","iconCaption":"Спортивный комплекс «ТРИУМФ»","marker-color":"#793d0e"}},{"type":"Feature","id":7,"geometry":{"type":"Point","coordinates":[34.408158,53.837837]},"properties":{"description":"Стадион «Кронтиф», г. Людиново, ул. Герцена 15А","iconCaption":"Стадион «Кронтиф» ","marker-color":"#793d0e"}}]}
